PyUnfold-0.5.0.dist-info/METADATA
PyUnfold-0.5.0.dist-info/RECORD
PyUnfold-0.5.0.dist-info/WHEEL
PyUnfold-0.5.0.dist-info/top_level.txt
pyunfold/__init__.py
pyunfold/__version__.py
pyunfold/callbacks.py
pyunfold/mix.py
pyunfold/priors.py
pyunfold/teststat.py
pyunfold/unfold.py
pyunfold/utils.py
pyunfold/tests/__init__.py
pyunfold/tests/conftest.py
pyunfold/tests/example.py
pyunfold/tests/example2.py
pyunfold/tests/example_non_square.py
pyunfold/tests/fixtures.py
pyunfold/tests/test_callbacks.py
pyunfold/tests/test_init.py
pyunfold/tests/test_mix.py
pyunfold/tests/test_priors.py
pyunfold/tests/test_teststat.py
pyunfold/tests/test_unfold.py
pyunfold/tests/test_utils.py
pyunfold/tests/testing_utils.py
