Metadata-Version: 2.1
Name: PyUnfold
Version: 0.5.0
Summary: PyUnfold: A Python package for iterative unfolding
Home-page: https://github.com/jrbourbeau/pyunfold
Author: James Bourbeau
Author-email: james@jamesbourbeau.com
License: MIT
Platform: UNKNOWN
Classifier: Development Status :: 4 - Beta
Classifier: Environment :: Console
Classifier: Intended Audience :: Science/Research
Classifier: Topic :: Scientific/Engineering
Classifier: License :: OSI Approved :: MIT License
Classifier: Programming Language :: Python
Classifier: Programming Language :: Python :: 2
Classifier: Programming Language :: Python :: 2.7
Classifier: Programming Language :: Python :: 3
Classifier: Programming Language :: Python :: 3.4
Classifier: Programming Language :: Python :: 3.5
Classifier: Programming Language :: Python :: 3.6
Provides-Extra: dev
Requires-Dist: numpy
Requires-Dist: scipy
Requires-Dist: pandas
Requires-Dist: six
Provides-Extra: dev
Requires-Dist: sphinx; extra == 'dev'
Requires-Dist: numpydoc; extra == 'dev'
Requires-Dist: sphinx-rtd-theme; extra == 'dev'
Requires-Dist: nbsphinx; extra == 'dev'
Requires-Dist: pandoc; extra == 'dev'
Requires-Dist: jupyter; extra == 'dev'
Requires-Dist: matplotlib; extra == 'dev'
Requires-Dist: seaborn; extra == 'dev'
Requires-Dist: pytest; extra == 'dev'
Requires-Dist: pytest-cov; extra == 'dev'
Requires-Dist: flake8; extra == 'dev'
Requires-Dist: tables; extra == 'dev'
Requires-Dist: twine; extra == 'dev'
